pybuilder_semver_git_tag/__init__.py
pybuilder_semver_git_tag/version.py
pybuilder_semver_git_tag-1.2.1.dist-info/DESCRIPTION.rst
pybuilder_semver_git_tag-1.2.1.dist-info/METADATA
pybuilder_semver_git_tag-1.2.1.dist-info/RECORD
pybuilder_semver_git_tag-1.2.1.dist-info/WHEEL
pybuilder_semver_git_tag-1.2.1.dist-info/metadata.json
pybuilder_semver_git_tag-1.2.1.dist-info/namespace_packages.txt
pybuilder_semver_git_tag-1.2.1.dist-info/top_level.txt
pybuilder_semver_git_tag-1.2.1.dist-info/zip-safe
